{"session_id": 59, "bill_id": 20191, "bill_type": "House Bill", "bill_number": 1117, "bill_title": "revise provisions regarding bond for persons charged with certain crimes involving methamphetamine.", "sponsors": [{"legislator_profile_id": 3361, "is_prime": true}, {"legislator_profile_id": 3406, "is_prime": true}, {"legislator_profile_id": 3418, "is_prime": false}], "keywords": ["Criminal Procedure", "Drugs"], "audio": [{"meeting_datetime": "2006-01-23T00:00:00-06:00", "committee": "HJU", "url": "https://sdpb.sd.gov/sdpbpodcast/2006/hju09.mp3", "start_seconds": 3519.0}, {"meeting_datetime": "2006-01-23T00:00:00-06:00", "committee": "HJU", "url": "https://sdpb.sd.gov/sdpbpodcast/2006/hju09.mp3", "start_seconds": 3519.0}, {"meeting_datetime": "2006-01-23T00:00:00-06:00", "committee": "HJU", "url": "https://sdpb.sd.gov/sdpbpodcast/2006/hju09.mp3", "start_seconds": 3519.0}], "bill_versions": [{"bill_id": 20191, "bill_version_id": 106749, "bill_version": "Introduced", "bill_version_date": "2006-01-19T09:54:41-06:00", "bill_text": "FOR AN ACT ENTITLED, An Act to revise provisions regarding bond for persons charged with certain crimes involving methamphetamine. BE IT ENACTED BY THE LEGISLATURE OF THE STATE OF SOUTH DAKOTA: Section 1. That chapter 23A-43 be amended by adding thereto a NEW SECTION to read as follows: In any bond hearing for any person who is charged with manufacturing, distributing, or dispensing methamphetamine; possessing with intent to manufacture, distribute, or dispense methamphetamine; creating or distributing a counterfeit of methamphetamine; or possessing methamphetamine with intent to distribute, there is a rebuttable presumption that the person charged is a threat to the community and a possible flight risk. 250 copies of this document were printed by the South Dakota Legislative Research Council at a cost of $.038 per page. . Insertions into existing statutes are indicated by underscores. Deletions from existing statutes are indicated by overstrikes."}], "amendments": [], "fiscal_notes": [], "action_log": [{"bill_id": 20191, "action_date": "2006-01-19T14:00:00-06:00", "document_id": 106834, "document_url": "https://mylrc.sdlegislature.gov/api/Documents/106834.pdf", "status_text": "First read in House and referred to", "journal_page": 140, "committee_id_action": 893, "committee_id_assigned": 891, "result": "N", "vote": {}}, {"bill_id": 20191, "action_date": "2006-01-23T07:45:00-06:00", "document_id": 107016, "document_url": "https://mylrc.sdlegislature.gov/api/Documents/107016.pdf", "status_text": "Scheduled for Committee hearing on this date", "journal_page": null, "committee_id_action": 891, "committee_id_assigned": null, "result": "N", "vote": {}}, {"bill_id": 20191, "action_date": "2006-01-23T07:45:00-06:00", "document_id": 107016, "document_url": "https://mylrc.sdlegislature.gov/api/Documents/107016.pdf", "status_text": "Deferred to 36th legislative day", "journal_page": 173, "committee_id_action": 891, "committee_id_assigned": null, "result": "P", "vote": {"vote_id": 63394, "president_vote": null, "Yea": [3387, 3393, 3401, 3407, 3429, 3434, 3444, 3461, 3371], "Excused": [3426], "Nay": [3448, 3456, 3406]}}], "rss_feed": "https://sdlegislature.gov/api/Bills/RSS/20191"}