{"session_id": 61, "bill_id": 21476, "bill_type": "House Bill", "bill_number": 1194, "bill_title": "authorize the disclosure of certain confidential information when a person who is subject to commitment proceedings has communicated a serious threat of serious physical injury against a reasonably identifiable victim.", "sponsors": [{"legislator_profile_id": 3627, "is_prime": true}, {"legislator_profile_id": 3637, "is_prime": true}, {"legislator_profile_id": 3571, "is_prime": false}, {"legislator_profile_id": 3572, "is_prime": false}, {"legislator_profile_id": 3573, "is_prime": false}, {"legislator_profile_id": 3610, "is_prime": false}, {"legislator_profile_id": 3651, "is_prime": false}, {"legislator_profile_id": 3653, "is_prime": false}, {"legislator_profile_id": 3658, "is_prime": false}, {"legislator_profile_id": 3674, "is_prime": false}], "keywords": ["Mental Disabilities", "Public Records"], "audio": [{"meeting_datetime": "2007-02-07T00:00:00-06:00", "committee": "HJU", "url": "https://sdpb.sd.gov/sdpbpodcast/2007/hju21.mp3", "start_seconds": 7102.0}, {"meeting_datetime": "2007-02-07T00:00:00-06:00", "committee": "HJU", "url": "https://sdpb.sd.gov/sdpbpodcast/2007/hju21.mp3", "start_seconds": 7102.0}, {"meeting_datetime": "2007-02-07T00:00:00-06:00", "committee": "HJU", "url": "https://sdpb.sd.gov/sdpbpodcast/2007/hju21.mp3", "start_seconds": 7102.0}, {"meeting_datetime": "2007-02-07T00:00:00-06:00", "committee": "HJU", "url": "https://sdpb.sd.gov/sdpbpodcast/2007/hju21.mp3", "start_seconds": 7102.0}, {"meeting_datetime": "2007-02-07T00:00:00-06:00", "committee": "HJU", "url": "https://sdpb.sd.gov/sdpbpodcast/2007/hju21.mp3", "start_seconds": 7102.0}, {"meeting_datetime": "2007-02-12T00:00:00-06:00", "committee": "HOU", "url": "https://sdpb.sd.gov/sdpbpodcast/2007/hou24.mp3", "start_seconds": 3355.0}, {"meeting_datetime": "2007-02-12T00:00:00-06:00", "committee": "HOU", "url": "https://sdpb.sd.gov/sdpbpodcast/2007/hou24.mp3", "start_seconds": 3355.0}, {"meeting_datetime": "2007-02-12T00:00:00-06:00", "committee": "HOU", "url": "https://sdpb.sd.gov/sdpbpodcast/2007/hou24.mp3", "start_seconds": 3355.0}, {"meeting_datetime": "2007-02-23T00:00:00-06:00", "committee": "SJU", "url": "https://sdpb.sd.gov/sdpbpodcast/2007/sju31.mp3", "start_seconds": 4809.0}, {"meeting_datetime": "2007-02-23T00:00:00-06:00", "committee": "SJU", "url": "https://sdpb.sd.gov/sdpbpodcast/2007/sju31.mp3", "start_seconds": 4809.0}, {"meeting_datetime": "2007-02-23T00:00:00-06:00", "committee": "SJU", "url": "https://sdpb.sd.gov/sdpbpodcast/2007/sju31.mp3", "start_seconds": 4809.0}, {"meeting_datetime": "2007-02-23T00:00:00-06:00", "committee": "SJU", "url": "https://sdpb.sd.gov/sdpbpodcast/2007/sju31.mp3", "start_seconds": 4809.0}], "bill_versions": [{"bill_id": 21476, "bill_version_id": 110783, "bill_version": "Introduced", "bill_version_date": "2007-01-25T09:51:33-06:00", "bill_text": "FOR AN ACT ENTITLED, An Act to authorize the disclosure of certain confidential information when a person who is subject to commitment proceedings has communicated a serious threat of serious physical injury against a reasonably identifiable victim. BE IT ENACTED BY THE LEGISLATURE OF THE STATE OF SOUTH DAKOTA: Section 1. That \u00a7 27A-12-29 be amended to read as follows: 27A-12-29. Information may be disclosed in the discretion of the holder of the record: (1) As necessary or beneficial in order for the person, or persons acting on behalf of the person, to apply for and acquire benefits for the person, including third-party financial payments, assistance, or services and follow-up, care, and treatment by local centers serving the area to which a person is expected to go upon temporary or permanent release or discharge; or (2) As necessary or beneficial for evaluation and accreditation; or (3) As necessary or beneficial to train persons enrolled in an accredited course leading to a degree and qualification, certification, or registration as a qualified mental health professional, licensed practical nurse, registered nurse, psychologist, social worker, physical therapist, occupational therapist, laboratory technician, medical records professional, dietician, or other health care professional; or (4) Upon request of the Human Services Center, with disclosure of records limited to relevant medical and psychiatric records ; or (5) If any person subject to the proceedings under this chapter has communicated a serious threat of serious physical injury against a reasonably identifiable victim, the person with knowledge of the threat may disclose the threat to the potential victim or to any law enforcement officer, or both. No cause of action may arise under this chapter against the person who discloses the threat to a potential victim or law enforcement officer pursuant to the provisions of this subdivision ."}, {"bill_id": 21476, "bill_version_id": 111753, "bill_version": "House Judiciary Engrossed", "bill_version_date": "2007-02-07T14:10:10-06:00", "bill_text": "FOR AN ACT ENTITLED, An Act to authorize the disclosure of certain confidential information when a person who is subject to commitment proceedings has communicated a serious threat of serious physical injury against a reasonably identifiable victim. BE IT ENACTED BY THE LEGISLATURE OF THE STATE OF SOUTH DAKOTA: Section 1. That \u00a7 27A-12-29 be amended to read as follows: 27A-12-29. Information may be disclosed in the discretion of the holder of the record: (1) As necessary or beneficial in order for the person, or persons acting on behalf of the person, to apply for and acquire benefits for the person, including third-party financial payments, assistance, or services and follow-up, care, and treatment by local centers serving the area to which a person is expected to go upon temporary or permanent release or discharge; or (2) As necessary or beneficial for evaluation and accreditation; or (3) As necessary or beneficial to train persons enrolled in an accredited course leading to a degree and qualification, certification, or registration as a qualified mental health professional, licensed practical nurse, registered nurse, psychologist, social worker, physical therapist, occupational therapist, laboratory technician, medical records professional, dietician, or other health care professional; or (4) Upon request of the Human Services Center, with disclosure of records limited to relevant medical and psychiatric records ; or (5) If any person subject to the proceedings under this chapter has communicated a serious threat of serious physical injury against a reasonably identifiable victim, the person with knowledge of the threat may disclose the threat to the potential victim or to any law enforcement officer, or both. No cause of action may arise under this chapter against the person who, in good faith, discloses the threat to a potential victim or law enforcement officer pursuant to the provisions of this subdivision ."}, {"bill_id": 21476, "bill_version_id": 112995, "bill_version": "Enrolled", "bill_version_date": "2007-02-28T08:40:10-06:00", "bill_text": ""}], "amendments": [], "fiscal_notes": [], "action_log": [{"bill_id": 21476, "action_date": "2007-01-25T14:00:00-06:00", "document_id": 110857, "document_url": "https://mylrc.sdlegislature.gov/api/Documents/110857.pdf", "status_text": "First read in House and referred to", "journal_page": 201, "committee_id_action": 923, "committee_id_assigned": 921, "result": "N", "vote": {}}, {"bill_id": 21476, "action_date": "2007-02-07T07:30:00-06:00", "document_id": 111725, "document_url": "https://mylrc.sdlegislature.gov/api/Documents/111725.pdf", "status_text": "Scheduled for Committee hearing on this date", "journal_page": null, "committee_id_action": 921, "committee_id_assigned": null, "result": "N", "vote": {}}, {"bill_id": 21476, "action_date": "2007-02-07T07:30:00-06:00", "document_id": 111725, "document_url": "https://mylrc.sdlegislature.gov/api/Documents/111725.pdf", "status_text": "Do Pass Amended,", "journal_page": 375, "committee_id_action": 921, "committee_id_assigned": null, "result": "P", "vote": {"vote_id": 64746, "president_vote": null, "Yea": [3579, 3592, 3594, 3598, 3599, 3619, 3632, 3638, 3651, 3672, 3676, 3582], "Excused": [3673]}}, {"bill_id": 21476, "action_date": "2007-02-09T13:00:00-06:00", "document_id": 111953, "document_url": "https://mylrc.sdlegislature.gov/api/Documents/111953.pdf", "status_text": "Deferred to another day", "journal_page": 434, "committee_id_action": 923, "committee_id_assigned": null, "result": "P", "vote": {}}, {"bill_id": 21476, "action_date": "2007-02-12T14:00:00-06:00", "document_id": 112085, "document_url": "https://mylrc.sdlegislature.gov/api/Documents/112085.pdf", "status_text": "Do Pass Amended,", "journal_page": 466, "committee_id_action": 923, "committee_id_assigned": null, "result": "P", "vote": {"vote_id": 67091, "president_vote": null, "Yea": [3572, 3576, 3577, 3578, 3579, 3580, 3581, 3582, 3583, 3586, 3587, 3588, 3590, 3591, 3592, 3593, 3594, 3597, 3598, 3599, 3600, 3604, 3605, 3606, 3609, 3611, 3613, 3616, 3619, 3620, 3622, 3624, 3628, 3629, 3631, 3632, 3635, 3637, 3638, 3640, 3642, 3643, 3644, 3645, 3646, 3648, 3649, 3650, 3651, 3653, 3654, 3655, 3656, 3657, 3658, 3660, 3662, 3663, 3665, 3666, 3668, 3672, 3673, 3674, 3675, 3676, 3584], "Excused": [3614, 3670], "Nay": [3671]}}, {"bill_id": 21476, "action_date": "2007-02-13T14:00:00-06:00", "document_id": 112192, "document_url": "https://mylrc.sdlegislature.gov/api/Documents/112192.pdf", "status_text": "First read in Senate and referred to", "journal_page": 494, "committee_id_action": 924, "committee_id_assigned": 902, "result": "N", "vote": {}}, {"bill_id": 21476, "action_date": "2007-02-23T10:00:00-06:00", "document_id": 112780, "document_url": "https://mylrc.sdlegislature.gov/api/Documents/112780.pdf", "status_text": "Scheduled for Committee hearing on this date", "journal_page": null, "committee_id_action": 902, "committee_id_assigned": null, "result": "N", "vote": {}}, {"bill_id": 21476, "action_date": "2007-02-23T10:00:00-06:00", "document_id": 112780, "document_url": "https://mylrc.sdlegislature.gov/api/Documents/112780.pdf", "status_text": "Do Pass,", "journal_page": 650, "committee_id_action": 902, "committee_id_assigned": null, "result": "P", "vote": {"vote_id": 65613, "president_vote": null, "Yea": [3571, 3573, 3612, 3626, 3659, 3667, 3627]}}, {"bill_id": 21476, "action_date": "2007-02-23T10:00:00-06:00", "document_id": 112780, "document_url": "https://mylrc.sdlegislature.gov/api/Documents/112780.pdf", "status_text": "Place on Consent Calendar", "journal_page": null, "committee_id_action": 902, "committee_id_assigned": null, "result": "P", "vote": {}}, {"bill_id": 21476, "action_date": "2007-02-27T14:00:00-06:00", "document_id": 112964, "document_url": "https://mylrc.sdlegislature.gov/api/Documents/112964.pdf", "status_text": "Do Pass Amended,", "journal_page": 683, "committee_id_action": 924, "committee_id_assigned": null, "result": "P", "vote": {"vote_id": 65762, "president_vote": null, "Yea": [3571, 3573, 3574, 3575, 3585, 3589, 3596, 3602, 3603, 3607, 3608, 3610, 3612, 3615, 3617, 3618, 3621, 3623, 3625, 3626, 3627, 3630, 3633, 3634, 3636, 3639, 3641, 3647, 3652, 3659, 3661, 3664, 3667, 3669], "Excused": [3595]}}, {"bill_id": 21476, "action_date": "2007-02-28T14:00:00-06:00", "document_id": 113110, "document_url": "https://mylrc.sdlegislature.gov/api/Documents/113110.pdf", "status_text": "Signed by Speaker", "journal_page": 721, "committee_id_action": 923, "committee_id_assigned": null, "result": "N", "vote": {}}, {"bill_id": 21476, "action_date": "2007-03-01T10:00:00-06:00", "document_id": 113232, "document_url": "https://mylrc.sdlegislature.gov/api/Documents/113232.pdf", "status_text": "Signed by President", "journal_page": 731, "committee_id_action": 924, "committee_id_assigned": null, "result": "N", "vote": {}}, {"bill_id": 21476, "action_date": "2007-03-02T10:00:00-06:00", "document_id": 113289, "document_url": "https://mylrc.sdlegislature.gov/api/Documents/113289.pdf", "status_text": "Delivered to the Governor", "journal_page": 792, "committee_id_action": 923, "committee_id_assigned": null, "result": "N", "vote": {}}, {"bill_id": 21476, "action_date": "2007-03-26T10:00:00-05:00", "document_id": 113416, "document_url": "https://mylrc.sdlegislature.gov/api/Documents/113416.pdf", "status_text": "Signed by Governor", "journal_page": 848, "committee_id_action": 923, "committee_id_assigned": null, "result": "N", "vote": {}}], "session_law": 3722, "rss_feed": "https://sdlegislature.gov/api/Bills/RSS/21476"}