{"session_id": 45, "bill_id": 12893, "bill_type": "House Bill", "bill_number": 1099, "bill_title": "to revise certain provisions relating to liens.", "sponsors": [{"legislator_profile_id": 1903, "is_prime": true}, {"legislator_profile_id": 1956, "is_prime": true}, {"legislator_profile_id": 1890, "is_prime": false}, {"legislator_profile_id": 1894, "is_prime": false}, {"legislator_profile_id": 1904, "is_prime": false}, {"legislator_profile_id": 1919, "is_prime": false}], "keywords": ["Boats & Personal Watercraft", "Liens", "Motor Vehicles", "Signed by Governor"], "audio": [], "bill_versions": [{"bill_id": 12893, "bill_version_id": 73193, "bill_version": "Introduced", "bill_version_date": "1997-01-27T00:00:00-06:00", "bill_text": "FOR AN ACT ENTITLED, An Act to revise certain provisions relating to liens. BE IT ENACTED BY THE LEGISLATURE OF THE STATE OF SOUTH DAKOTA: Section 1. That \u00a7 32-3-41 be amended to read as follows: 32-3-41. Any mortgage, conveyance intended to operate as a mortgage, conditional sales contract Any security interest , mechanic's lien, or similar instrument other than a financing statement covering a motor vehicle, trailer , or semitrailer, if the instrument is accompanied by delivery of the manufacturer's statement of origin or the manufacturer's certificate of origin and followed by actual and continued possession of the same by the holder of the instrument, or in the case of the certificate of title, if a notation of same has been made by the secretary or county register of deeds on the face thereof or if notation of same has been made by the seller, buyer, owner, or holder of the instrument on the reverse thereof , shall be valid against the creditors of the mortgagor debtor , whether armed with process or not, and subsequent purchasers , mortgagees and other lien holders or claimants, but otherwise is not valid against them. Section 2. That \u00a7 42-8-82 be amended to read as follows: 42-8-82. A security interest created in this state in a large boat, and as defined by \u00a7 \u00a7 42-8-71 to 42-8-74, inclusive, and \u00a7 \u00a7 42-8-76 to 42-8-84, inclusive, on and after March 1, 1992, is not perfected until the security interest is noted on the certificate of title. On or after July 1, 1993, a security interest created in this state on a large boat, as defined in \u00a7 42-8-2, exclusive of a motorboat is not perfected until the security interest is noted on the certificate of title. On or after July 1, 1994, a security interest created in this state on a large boat, as defined in \u00a7 42-8-2, is not perfected until the security interest is noted on the certificate of title. To perfect the security interest, a copy of the security agreement shall be presented along with the original title. The register of deeds , or the seller, buyer, owner, or holder of the instrument shall note the security interest on the face of the title at any place on the instrument, and if so noted, the lien shall be perfected against the creditors of the debtor, shall be valid against the creditors of the debtor, whether armed with process or not, and subsequent purchasers and other lien holders or claimants, but otherwise is not valid against them . The fee for noting the lien is five dollars. The fees shall be credited to the county general fund. The certificate of title shall be presented to the county register of deeds if a lien is to be noted on an existing certificate of title. The owner shall present the certificate of title to the county register of deeds when a release statement is filed."}, {"bill_id": 12893, "bill_version_id": 73192, "bill_version": "Enrolled", "bill_version_date": "1997-02-11T00:00:00-06:00", "bill_text": ""}], "amendments": [], "fiscal_notes": [], "action_log": [{"bill_id": 12893, "action_date": "1997-01-27T14:00:00-06:00", "document_id": 72884, "document_url": "https://mylrc.sdlegislature.gov/api/Documents/72884.pdf", "status_text": "First read in House and referred to", "journal_page": 153, "committee_id_action": 544, "committee_id_assigned": 542, "result": "N", "vote": {}}, {"bill_id": 12893, "action_date": "1997-01-31T07:45:00-06:00", "document_id": 72257, "document_url": "https://mylrc.sdlegislature.gov/api/Documents/72257.pdf", "status_text": "Do Pass,", "journal_page": null, "committee_id_action": 542, "committee_id_assigned": null, "result": "P", "vote": {"vote_id": 37713, "president_vote": null, "Yea": [1931, 1924, 1892, 1894, 1903, 1910, 1918, 1951, 1968, 1898, 1922, 1954, 1982]}}, {"bill_id": 12893, "action_date": "1997-02-03T14:00:00-06:00", "document_id": 72894, "document_url": "https://mylrc.sdlegislature.gov/api/Documents/72894.pdf", "status_text": "Do Pass,", "journal_page": 278, "committee_id_action": 544, "committee_id_assigned": null, "result": "P", "vote": {"vote_id": 36804, "president_vote": null, "Yea": [1886, 1887, 1888, 1890, 1891, 1892, 1894, 1895, 1896, 1897, 1898, 1899, 1900, 1902, 1903, 1904, 1906, 1907, 1909, 1910, 1913, 1914, 1916, 1917, 1918, 1921, 1922, 1923, 1926, 1929, 1931, 1933, 1934, 1936, 1937, 1940, 1941, 1942, 1943, 1944, 1947, 1948, 1949, 1950, 1951, 1952, 1954, 1957, 1958, 1961, 1962, 1963, 1964, 1966, 1967, 1968, 1970, 1971, 1973, 1974, 1975, 1980, 1982, 1983, 1984, 1985, 1987, 1988, 1924], "Nay": [1953]}}, {"bill_id": 12893, "action_date": "1997-02-04T14:00:00-06:00", "document_id": 72897, "document_url": "https://mylrc.sdlegislature.gov/api/Documents/72897.pdf", "status_text": "First read in Senate and referred to", "journal_page": 314, "committee_id_action": 545, "committee_id_assigned": 523, "result": "N", "vote": {}}, {"bill_id": 12893, "action_date": "1997-02-07T10:00:00-06:00", "document_id": 72313, "document_url": "https://mylrc.sdlegislature.gov/api/Documents/72313.pdf", "status_text": "Scheduled for Committee hearing on this date", "journal_page": null, "committee_id_action": 523, "committee_id_assigned": null, "result": "N", "vote": {}}, {"bill_id": 12893, "action_date": "1997-02-07T10:00:00-06:00", "document_id": 72313, "document_url": "https://mylrc.sdlegislature.gov/api/Documents/72313.pdf", "status_text": "Do Pass,", "journal_page": 350, "committee_id_action": 523, "committee_id_assigned": null, "result": "P", "vote": {"vote_id": 37372, "president_vote": null, "Yea": [1884, 1901, 1912, 1919, 1979, 1956, 1986]}}, {"bill_id": 12893, "action_date": "1997-02-07T10:00:00-06:00", "document_id": 72313, "document_url": "https://mylrc.sdlegislature.gov/api/Documents/72313.pdf", "status_text": "Place on Consent Calendar", "journal_page": 350, "committee_id_action": 523, "committee_id_assigned": null, "result": "P", "vote": {}}, {"bill_id": 12893, "action_date": "1997-02-10T14:00:00-06:00", "document_id": 72905, "document_url": "https://mylrc.sdlegislature.gov/api/Documents/72905.pdf", "status_text": "Do Pass,", "journal_page": 372, "committee_id_action": 545, "committee_id_assigned": null, "result": "P", "vote": {"vote_id": 35994, "president_vote": null, "Yea": [1884, 1885, 1889, 1893, 1901, 1905, 1908, 1911, 1912, 1915, 1919, 1920, 1925, 1927, 1928, 1930, 1932, 1935, 1938, 1939, 1945, 1946, 1955, 1956, 1959, 1960, 1965, 1969, 1972, 1976, 1977, 1978, 1979, 1981, 1986]}}, {"bill_id": 12893, "action_date": "1997-02-12T14:00:00-06:00", "document_id": 72908, "document_url": "https://mylrc.sdlegislature.gov/api/Documents/72908.pdf", "status_text": "Signed by Speaker", "journal_page": 457, "committee_id_action": 544, "committee_id_assigned": null, "result": "N", "vote": {}}, {"bill_id": 12893, "action_date": "1997-02-13T14:00:00-06:00", "document_id": 72911, "document_url": "https://mylrc.sdlegislature.gov/api/Documents/72911.pdf", "status_text": "Signed by President", "journal_page": 439, "committee_id_action": 545, "committee_id_assigned": null, "result": "N", "vote": {}}, {"bill_id": 12893, "action_date": "1997-02-18T14:00:00-06:00", "document_id": 72916, "document_url": "https://mylrc.sdlegislature.gov/api/Documents/72916.pdf", "status_text": "Delivered to the Governor", "journal_page": 526, "committee_id_action": 544, "committee_id_assigned": null, "result": "N", "vote": {}}, {"bill_id": 12893, "action_date": "1997-02-24T14:00:00-06:00", "document_id": 72924, "document_url": "https://mylrc.sdlegislature.gov/api/Documents/72924.pdf", "status_text": "Signed by Governor", "journal_page": 644, "committee_id_action": 544, "committee_id_assigned": null, "result": "N", "vote": {}}], "session_law": 678}